{
  "from": "USD",
  "to": {
    "AED": 3.672505,
    "AFN": 70.00051,
    "ALL": 84.75049,
    "AMD": 382.549591,
    "ANG": 1.789982,
    "AOA": 917.000107,
    "ARS": 1480.204955,
    "AUD": 1.531874,
    "AWG": 1.8,
    "AZN": 1.703525,
    "BAM": 1.698148,
    "BBD": 2.013771,
    "BDT": 122.03434,
    "BGN": 1.69979,
    "BHD": 0.377017,
    "BIF": 2940,
    "BMD": 1,
    "BND": 1.303523,
    "BOB": 6.933977,
    "BRL": 5.357301,
    "BSD": 0.999805,
    "BTC": 0.000009336109,
    "BTN": 88.702409,
    "BWP": 13.42427,
    "BYN": 3.408539,
    "BYR": 19600,
    "BZD": 2.010897,
    "CAD": 1.406785,
    "CDF": 2260.000439,
    "CHF": 0.809505,
    "CLF": 0.023937,
    "CLP": 939.029776,
    "CNY": 7.12106,
    "CNH": 7.128515,
    "COP": 3856.45,
    "CRC": 501.682259,
    "CUC": 1,
    "CUP": 26.5,
    "CVE": 96.10062,
    "CZK": 21.148971,
    "DJF": 177.720213,
    "DKK": 6.488185,
    "DOP": 64.249797,
    "DZD": 130.593337,
    "EGP": 47.198203,
    "ERN": 15,
    "ETB": 152.625013,
    "EUR": 0.86908,
    "FJD": 2.27695,
    "FKP": 0.760358,
    "GBP": 0.762025,
    "GEL": 2.719796,
    "GGP": 0.760358,
    "GHS": 10.925006,
    "GIP": 0.760358,
    "GMD": 73.488667,
    "GNF": 8690.000175,
    "GTQ": 7.662453,
    "GYD": 209.181879,
    "HKD": 7.77256,
    "HNL": 26.350191,
    "HRK": 6.547803,
    "HTG": 130.907986,
    "HUF": 336.473007,
    "IDR": 16744.15,
    "ILS": 3.259098,
    "IMP": 0.760358,
    "INR": 88.78425,
    "IQD": 1310,
    "IRR": 42112.501318,
    "ISK": 126.370371,
    "JEP": 0.760358,
    "JMD": 160.4897,
    "JOD": 0.70903,
    "JPY": 154.26898,
    "KES": 129.203383,
    "KGS": 87.449028,
    "KHR": 4015.000184,
    "KMF": 426.000319,
    "KPW": 899.999893,
    "KRW": 1439.107781,
    "KWD": 0.30717,
    "KYD": 0.833185,
    "KZT": 525.252876,
    "LAK": 21640.000255,
    "LBP": 89528.627431,
    "LKR": 304.395581,
    "LRD": 183.45027,
    "LSL": 17.65021,
    "LTL": 2.95274,
    "LVL": 0.60489,
    "LYD": 5.454999,
    "MAD": 9.309856,
    "MDL": 17.017157,
    "MGA": 4484.999915,
    "MKD": 53.402251,
    "MMK": 2099.812195,
    "MNT": 3586.185516,
    "MOP": 8.005209,
    "MRU": 40.039684,
    "MUR": 45.950086,
    "MVR": 15.40497,
    "MWK": 1737.000219,
    "MXN": 18.50847,
    "MYR": 4.205974,
    "MZN": 63.949739,
    "NAD": 17.649897,
    "NGN": 1442.249818,
    "NIO": 36.749862,
    "NOK": 10.141935,
    "NPR": 141.927109,
    "NZD": 1.75733,
    "OMR": 0.3845,
    "PAB": 0.999978,
    "PEN": 3.376968,
    "PGK": 4.211991,
    "PHP": 58.746987,
    "PKR": 282.250476,
    "PLN": 3.698445,
    "PYG": 7095.443791,
    "QAR": 3.640903,
    "RON": 4.419804,
    "RSD": 101.88201,
    "RUB": 80.99934,
    "RWF": 1449.5,
    "SAR": 3.750359,
    "SBD": 8.230592,
    "SCR": 15.025074,
    "SDG": 600.502758,
    "SEK": 9.49848,
    "SGD": 1.306175,
    "SHP": 0.750259,
    "SLE": 22.54951,
    "SLL": 20969.499529,
    "SOS": 571.502368,
    "SRD": 38.800499,
    "STD": 20697.981008,
    "STN": 21.5,
    "SVC": 8.748616,
    "SYP": 11056.756635,
    "SZL": 17.649649,
    "THB": 32.540497,
    "TJS": 9.228392,
    "TMT": 3.51,
    "TND": 2.89375,
    "TOP": 2.342104,
    "TRY": 42.079401,
    "TTD": 6.771582,
    "TWD": 30.912504,
    "TZS": 2459.615025,
    "UAH": 42.046756,
    "UGX": 3479.144236,
    "UYU": 39.853264,
    "UZS": 11990.000218,
    "VES": 223.682201,
    "VND": 26321.5,
    "VUV": 121.628578,
    "WST": 2.799576,
    "XAF": 569.545549,
    "XAG": 0.020863,
    "XAU": 0.000251,
    "XCD": 2.70255,
    "XCG": 1.801993,
    "XDR": 0.70875,
    "XOF": 569.501059,
    "XPF": 103.950258,
    "YER": 238.549801,
    "ZAR": 17.349704,
    "ZMK": 9001.198173,
    "ZMW": 22.271906,
    "ZWL": 321.999592
  }
}
